requestcord/__init__.py
requestcord/payloads.py
requestcord/common/__init__.py
requestcord/common/constants.py
requestcord/common/models.py
requestcord/common/response.py
requestcord/common/types.py
requestcord/common/utils.py
requestcord/sync_api/__init__.py
requestcord/sync_api/client.py
requestcord/sync_api/http.py
requestcord/sync_api/actions/__init__.py
requestcord/sync_api/actions/boosts.py
requestcord/sync_api/actions/forum.py
requestcord/sync_api/actions/guilds.py
requestcord/sync_api/actions/members.py
requestcord/sync_api/actions/messages.py
requestcord/sync_api/actions/reactions.py
requestcord/sync_api/actions/threads.py
requestcord/sync_api/actions/user.py
requestcord/utils/__init__.py
requestcord/utils/headers.py
requestcord-2.0.2.dist-info/LICENSE
requestcord-2.0.2.dist-info/METADATA
requestcord-2.0.2.dist-info/WHEEL
requestcord-2.0.2.dist-info/top_level.txt
requestcord-2.0.2.dist-info/RECORD
