Metadata-Version: 2.1
Name: requestcord
Version: 2.0.2
Summary: Advanced Discord API wrapper with modern features
Author: Zkamo & VatosV2
License: MIT
Keywords: discord,api,wrapper,requestcord
Classifier: Programming Language :: Python :: 3
Classifier: License :: OSI Approved :: MIT License
Classifier: Operating System :: OS Independent
Requires-Python: >3.10
License-File: LICENSE
Requires-Dist: curl-cffi
Requires-Dist: websocket-client
Requires-Dist: discord-protos
Provides-Extra: win
Requires-Dist: pywin32>=306; sys_platform == "win32" and extra == "win"
